wordle/WordleGameMaster.py
wordle/__init__.py
wordle/bots/ModalLetter.py
wordle/bots/Random.py
wordle/bots/WordleBot.py
wordle/bots/__init__.py
wordle_ebarbeary-0.1.0.dist-info/LICENSE
wordle_ebarbeary-0.1.0.dist-info/METADATA
wordle_ebarbeary-0.1.0.dist-info/WHEEL
wordle_ebarbeary-0.1.0.dist-info/top_level.txt
wordle_ebarbeary-0.1.0.dist-info/RECORD
