Metadata-Version: 2.1
Name: wordle-ebarbeary
Version: 0.1.0
Summary: A suite of tools to build, test and run algorithms that solve the popular web-game 'Wordle'
Home-page: https://github.com/ebarbeary/wordle
Author: Elliot Barbeary
Author-email: e.barbeary@outlook.com
License: UNKNOWN
Project-URL: Bug Tracker, https://github.com/ebarbeary/wordle/issues
Platform: UNKNOWN
Requires-Python: >=3.6
License-File: LICENSE
